gcp_logger_helper/__init__.py
gcp_logger_helper-0.0.4.dist-info/LICENSE
gcp_logger_helper-0.0.4.dist-info/METADATA
gcp_logger_helper-0.0.4.dist-info/WHEEL
gcp_logger_helper-0.0.4.dist-info/top_level.txt
gcp_logger_helper-0.0.4.dist-info/RECORD
